qsm_forward/__init__.py
qsm_forward/main.py
qsm_forward/qsm_forward.py
qsm_forward-0.25.dist-info/licenses/LICENSE
qsm_forward-0.25.dist-info/METADATA
qsm_forward-0.25.dist-info/WHEEL
qsm_forward-0.25.dist-info/entry_points.txt
qsm_forward-0.25.dist-info/top_level.txt
qsm_forward-0.25.dist-info/RECORD
