Metadata-Version: 2.4
Name: qsm-forward
Version: 0.25
Summary: A forward-model simulation for Quantitative Susceptibility Mapping
Home-page: https://github.com/astewartau/qsm-forward
Author: Ashley Stewart
Author-email: a.stewart.au@gmail.com
Classifier: Development Status :: 4 - Beta
Classifier: Intended Audience :: Science/Research
Classifier: License :: OSI Approved :: GNU General Public License v3 (GPLv3)
Classifier: Programming Language :: Python :: 3
Classifier: Programming Language :: Python :: 3.8
License-File: LICENSE
Requires-Dist: numpy
Requires-Dist: nilearn
Requires-Dist: dipy
Dynamic: author
Dynamic: author-email
Dynamic: classifier
Dynamic: description
Dynamic: description-content-type
Dynamic: home-page
Dynamic: license-file
Dynamic: requires-dist
Dynamic: summary
